FetcherNews/NewsApi.py
FetcherNews/__init__.py
FetcherNews-1.0.dist-info/LICENCE
FetcherNews-1.0.dist-info/METADATA
FetcherNews-1.0.dist-info/WHEEL
FetcherNews-1.0.dist-info/top_level.txt
FetcherNews-1.0.dist-info/RECORD
